flaskr/__init__.py
flaskr/auth.py
flaskr/blog.py
flaskr/db.py
flaskr/schema.sql
flaskr/static/style.css
flaskr/templates/base.html
flaskr/templates/auth/login.html
flaskr/templates/auth/register.html
flaskr/templates/blog/create.html
flaskr/templates/blog/index.html
flaskr/templates/blog/update.html
pubclient/__init__.py
pubclient/_impl/__init__.py
pubclient/_impl/pubclient.py
demoaction-1.0.2.dist-info/METADATA
demoaction-1.0.2.dist-info/WHEEL
demoaction-1.0.2.dist-info/top_level.txt
demoaction-1.0.2.dist-info/RECORD
